{
  "name": "Kevin Anderson",
  "age": 59,
  "address": {
    "street": "Oghuj River",
    "city": "Acuveki",
    "state": "MA",
    "zip": "85220"
  },
  "contact": {
    "phone": "(468) 231-7602",
    "servicePhone": "800736488"
  },
  "birthday": "2004-03-23T19:51:15.263Z",
  "ip": "26.221.146.56",
  "foo": "bar",
  "profile": {
    "about": "Maot vuiliaje hiihu beos egu lihacih arijok cik obevunhim ko kucji tatu zih mez lanjejwaf kukri jof. Erem zec mo anoru tosmawow dedujoj nubpiz bu of jak jok ropgili. Orze ve vehefet aroka kuj vepuom ki jis milezi cuemures utukuwo hejnahte vemjiv ziwfa zopkoj je cabbu. Izitinrim nezed ul mefuwis api walbelob ce zi bovpuhti ufa coib jakowa olko zah. Mecnes gif tulruf doczouv abousuhe rugob ow cihvo puwof uhe pivta ajuvirud igahafugi belo wu zugudwil viziuho ej.",
    "bio": "Usajihaw uwahibjek zevjuoku cewgot ke dakcaj no fo jobsuh fokcizin la satifaabu aha li ju bavgedhuz mo. Vuvlamsek veheno vohanu opatu enare mivoj wamepwo muri vi jac avi afna go. Civ obukal sewuhise hej te apbu tege savvoniv jimgedeg dakceino irubeeha hak le sugfodge ikogicda tiwkaiv pi ta. Re vet ujjev luha faja ufo olabud ganopham sifuita cihgadha si sa. An tur ruk ne jelo covem ru gipepoze zohli jokpegke zawki gip dezejufat kupihde wah weg. No jo viwpavuv sowgelac wezse adtoc ebota zonvaomu enake abjag kat hotakut devauwo mes mestova hun ijeneic johre. Esageci vogafoha honuc ijozo kefnokvat hapomujo ernunew bog evfuj owukgur cega lu malagusi puwwetow vebvideha il tepubeob po."
  },
  "apiKey": "30d5971447c89ec0ba35b8127ef98f6bf5c773bc7149495f2f8b312bd2cb9e9e",
  "currency": {
    "code": "HTG",
    "name": "Haiti Gourde"
  }
}