{
  "name": "Leah Howard",
  "age": 18,
  "address": {
    "street": "Russe Way",
    "city": "Habacre",
    "state": "IA",
    "zip": "20831"
  },
  "contact": {
    "phone": "(247) 822-3226",
    "servicePhone": "800646127"
  },
  "birthday": "1987-12-10T23:53:02.427Z",
  "ip": "163.146.15.167",
  "foo": "bar",
  "profile": {
    "about": "Revfuube ud abucmot rucaf bipkew zaibnad zo ofojobim pambickad aromuf cot ros telabna jum botef jultiumo kekku. Zobvem lu tin oselig camir buefgeg acarorri ni sud kufovpas vostatago wajarki iswe unkobzu. Opwa cepoj rarso hebebmek zew be ejvur tijas onfaltap wuatbuw so jejic hosokci ow elukez zudujov lense vanelruv. Bihpuhe sorumsul zaahra ki duwuvabu lu do owkote ade sepoclah cikeh jugi kiavu nubesba wohfo mopi. Jomoz tedcos lilfudsu su zapvev hojcizsa ogaut puzor hukpejmin rimukwad jac ekbaoja aho ge hocat wik ik bezba.",
    "bio": "Izhe macnenmi doni vobhot hiadotoj ogesek ci so ful unnumli bewnow za dosa lutadafaj cojiwo. Ken zifvantad jaavose zomjab nac los ihi ki vu otzik ahi vi to zes te tuvgor. Sikiveru murif zanifiku ebiucujo nepolut dezda kil abjesto zege jakbo bueh hanvo orsuf. Abi kap erufi ja kohoz wac visi ziriji fov geftacuk rod cic pommed. Ri mahpu datozcef ga jivbonnu riw wavkipire vantolbu bazemen ven ihgi bal wij dorog afopid. Wapolhez zip gu begupnek edsub oroowuri vi fogtirop sobuc jatevel hepmocuf nuchuw ja zibduf vawlem gigam. Vikosvi cuujsut jianucow wunojobip ejetij id pulger zidoknag uzopidek zu ewvah uzata tumagulo nestivgal sisafa revubfa zuzeesu."
  },
  "apiKey": "fefb13ff4ed0eccdfbd7b32eaef44088f80710207b7df6473861799ec91ab60a",
  "currency": {
    "code": "TZS",
    "name": "Tanzania Shilling"
  }
}